rps/__init__.py
rps/__version__.py
rps/robotarium.py
rps/robotarium_abc.py
rps/examples/__init__.py
rps/utilities/__init__.py
rps/utilities/barrier_certificates.py
rps/utilities/barrier_certificates2.py
rps/utilities/controllers.py
rps/utilities/graph.py
rps/utilities/misc.py
rps/utilities/transformations.py
robotarium_python_simulator-0.0.0.dist-info/LICENSE
robotarium_python_simulator-0.0.0.dist-info/METADATA
robotarium_python_simulator-0.0.0.dist-info/WHEEL
robotarium_python_simulator-0.0.0.dist-info/top_level.txt
robotarium_python_simulator-0.0.0.dist-info/RECORD
