Metadata-Version: 2.1
Name: robotarium-python-simulator
Version: 0.0.0
Summary: A Python-based simulator for the Robotarium.
Home-page: https://github.com/robotarium/robotarium_python_simulator
Author: Sean Wilson and Paul Glotfelter
Author-email: Sean.T.Wilson@gatech.edu
License: MIT
Platform: UNKNOWN
Classifier: License :: OSI Approved :: MIT License
Classifier: Programming Language :: Python
Classifier: Programming Language :: Python :: 3.5
Classifier: Programming Language :: Python :: Implementation :: CPython
Requires-Dist: cvxopt
Requires-Dist: scipy
Requires-Dist: numpy
Requires-Dist: matplotlib
